Metadata-Version: 2.2
Name: bellem
Version: 0.0.1
Summary: My personal library
Home-page: https://github.com/bdsaglam/bellem
Author: Barış Deniz Sağlam
Author-email: bdsaglam@gmail.com
License: Apache Software License 2.0
Keywords: notebook
Classifier: Development Status :: 4 - Beta
Classifier: Intended Audience :: Developers
Classifier: Natural Language :: English
Classifier: Programming Language :: Python :: 3.10
Classifier: License :: OSI Approved :: Apache Software License
Requires-Python: >=3.10
License-File: LICENSE
Requires-Dist: fastcore
Requires-Dist: numpy
Requires-Dist: pandas
Requires-Dist: pydantic
Requires-Dist: tqdm
Provides-Extra: dev
Requires-Dist: nbdev; extra == "dev"
Requires-Dist: jupyter; extra == "dev"
Requires-Dist: matplotlib; extra == "dev"
Requires-Dist: twine; extra == "dev"
Requires-Dist: pre-commit; extra == "dev"
Requires-Dist: ruff; extra == "dev"
Requires-Dist: python-dotenv; extra == "dev"
Requires-Dist: typer; extra == "dev"
Requires-Dist: rich; extra == "dev"
Provides-Extra: full
Requires-Dist: nbdev; extra == "full"
Requires-Dist: jupyter; extra == "full"
Requires-Dist: matplotlib; extra == "full"
Requires-Dist: twine; extra == "full"
Requires-Dist: pre-commit; extra == "full"
Requires-Dist: ruff; extra == "full"
Requires-Dist: python-dotenv; extra == "full"
Requires-Dist: typer; extra == "full"
Requires-Dist: rich; extra == "full"
Requires-Dist: arize-phoenix; extra == "full"
Requires-Dist: datasets; extra == "full"
Requires-Dist: dspy; extra == "full"
Requires-Dist: evaluate; extra == "full"
Requires-Dist: fastai; extra == "full"
Requires-Dist: huggingface_hub; extra == "full"
Requires-Dist: llama-index; extra == "full"
Requires-Dist: magentic; extra == "full"
Requires-Dist: openai; extra == "full"
Requires-Dist: peft; extra == "full"
Requires-Dist: text-generation; extra == "full"
Requires-Dist: torch; extra == "full"
Requires-Dist: torchvision; extra == "full"
Requires-Dist: transformers; extra == "full"
Requires-Dist: trl; extra == "full"
Requires-Dist: wandb; extra == "full"
Dynamic: author
Dynamic: author-email
Dynamic: classifier
Dynamic: description
Dynamic: description-content-type
Dynamic: home-page
Dynamic: keywords
Dynamic: license
Dynamic: provides-extra
Dynamic: requires-dist
Dynamic: requires-python
Dynamic: summary
